jsSecrets.py
jssecrets-1.0.13.dist-info/licenses/LICENSE
jssecrets-1.0.13.dist-info/METADATA
jssecrets-1.0.13.dist-info/WHEEL
jssecrets-1.0.13.dist-info/entry_points.txt
jssecrets-1.0.13.dist-info/top_level.txt
jssecrets-1.0.13.dist-info/RECORD
