Metadata-Version: 2.4
Name: jssecrets
Version: 1.0.13
Summary: Find secrets in js files from a given url
Author-email: Diego <diego.espindola@gmail.com>
License-Expression: GPL-2.0
Requires-Python: >=3.8
License-File: LICENSE
Requires-Dist: requests
Dynamic: license-file
